wordhunt_package/__init__.py
wordhunt_package/english.py
wordhunt_package/solver.py
wordhunt_package/wordhunt.py
wordhunt_package/data/__init__.py
wordhunt_package/data/english.json
wordhunt_package-0.2.0.dist-info/METADATA
wordhunt_package-0.2.0.dist-info/WHEEL
wordhunt_package-0.2.0.dist-info/entry_points.txt
wordhunt_package-0.2.0.dist-info/top_level.txt
wordhunt_package-0.2.0.dist-info/RECORD
