Metadata-Version: 2.1
Name: wordhunt_package
Version: 0.2.0
Summary: Type "wordhunt" and enter your Wordhunt board to get all possible words in Wordhunt!
Home-page: https://github.com/jeffreykim/wordhunt-bot
Author: Jeffrey Kim
Author-email: jkjeffrey7@gmail.com
Classifier: Programming Language :: Python :: 3
Classifier: License :: OSI Approved :: MIT License
Classifier: Operating System :: OS Independent
Requires-Python: >=3.6
